gradle.properties
hexdoc_caduceus/__gradle_version__.py
hexdoc_caduceus/__init__.py
hexdoc_caduceus/__version__.py
hexdoc_caduceus/_hooks.py
hexdoc_caduceus/py.typed
hexdoc_caduceus/_export/.gitignore
hexdoc_caduceus/_export/__init__.py
hexdoc_caduceus/_export/generated/__init__.py
hexdoc_caduceus/_export/generated/caduceus.hexdoc.json
hexdoc_caduceus/_export/generated/caduceus.patterns.hexdoc.json
hexdoc_caduceus/_export/generated/assets/caduceus/lang/en_us.flatten.json5
hexdoc_caduceus/_export/generated/assets/caduceus/lang/zh_cn.flatten.json5
hexdoc_caduceus/_export/generated/assets/hexcasting/patchouli_books/thehexbook/en_us/entries/basics/caduceus_changes.json5
hexdoc_caduceus/_export/generated/assets/hexcasting/patchouli_books/thehexbook/en_us/entries/casting/caduceus_mishaps.json5
hexdoc_caduceus/_export/generated/assets/hexcasting/patchouli_books/thehexbook/en_us/entries/casting/continuations.json5
hexdoc_caduceus/_export/generated/assets/hexcasting/patchouli_books/thehexbook/en_us/entries/patterns/delimcc.json5
hexdoc_caduceus/_export/generated/assets/hexcasting/patchouli_books/thehexbook/en_us/entries/patterns/jump_manipulation.json5
hexdoc_caduceus/_templates/__init__.py
hexdoc_caduceus-0.2.1.1.20.1.1.0.dist-info/METADATA
hexdoc_caduceus-0.2.1.1.20.1.1.0.dist-info/WHEEL
hexdoc_caduceus-0.2.1.1.20.1.1.0.dist-info/entry_points.txt
hexdoc_caduceus-0.2.1.1.20.1.1.0.dist-info/licenses/LICENSE
hexdoc_caduceus-0.2.1.1.20.1.1.0.dist-info/RECORD
