Metadata-Version: 2.4
Name: hexdoc-caduceus
Version: 0.2.1.1.20.1.1.0
Summary: A Clojure-based Hex Casting addon for advanced meta-evaluation.
Project-URL: Homepage, https://caduceus.hexxy.media
Project-URL: Source, https://github.com/object-Object/Caduceus
Author: object-Object
License-File: LICENSE
Keywords: hexdoc
Requires-Python: >=3.11
Requires-Dist: hexdoc-hexcasting~=0.11.2.1.0
Provides-Extra: dev
Requires-Dist: ruff~=0.11.13; extra == 'dev'
